pydisque/__init__.py
pydisque/client.py
pydisque-0.1.5.dist-info/LICENSE.txt
pydisque-0.1.5.dist-info/METADATA
pydisque-0.1.5.dist-info/WHEEL
pydisque-0.1.5.dist-info/top_level.txt
pydisque-0.1.5.dist-info/RECORD
