Metadata-Version: 2.1
Name: pydisque
Version: 0.1.5
Summary: disque client
Home-page: http://github.com/ybrs/pydisque
Author: ybrs
Author-email: aybars.badur@gmail.com
License: MIT
Platform: UNKNOWN
Classifier: Development Status :: 4 - Beta
Classifier: Intended Audience :: Developers
Classifier: License :: OSI Approved :: MIT License
Classifier: Operating System :: OS Independent
Classifier: Programming Language :: Python
Classifier: Topic :: Database
Classifier: Topic :: Software Development :: Libraries :: Python Modules
Requires-Dist: redis
Requires-Dist: six
